exowirc/__init__.py
exowirc/calib_utils.py
exowirc/fit_utils.py
exowirc/io_utils.py
exowirc/photo_utils.py
exowirc/plot_utils.py
exowirc-0.0.1.dist-info/LICENSE
exowirc-0.0.1.dist-info/METADATA
exowirc-0.0.1.dist-info/WHEEL
exowirc-0.0.1.dist-info/top_level.txt
exowirc-0.0.1.dist-info/RECORD
